lprp_core/__init__.py
lprp_core/data/__init__.py
lprp_core/data/model/__init__.py
lprp_core/data/model/client.py
lprp_core/data/model/model_base.py
lprp_core/data/model/parking_garage.py
lprp_core/data/model/usage_log.py
lprp_core/data/model/user.py
lprp_core/data/model/vehicle.py
lprp_core/data/persistence_manager.py
lprp_core/data/schema/__init__.py
lprp_core/data/schema/healthcheck_service/__init__.py
lprp_core/data/schema/healthcheck_service/availabiltity_ping.py
lprp_core/data/schema/healthcheck_service/healtcheck_registration.py
lprp_core/exceptions/__init__.py
lprp_core/service.py
lprp_core/services/__init__.py
lprp_core/services/backend.py
lprp_core/services/gateway_client.py
lprp_core/services/hardware_simulator.py
lprp_core/services/healthcheck.py
lprp_core/services/license_plate_recognition.py
lprp_core/services/user_interface_backend.py
lprp_core/system_states/__init__.py
lprp_core/system_states/gate_state.py
lprp_core/system_states/visual_indicator_state.py
lprp_core-1.0.0.dist-info/METADATA
lprp_core-1.0.0.dist-info/WHEEL
lprp_core-1.0.0.dist-info/RECORD
