Metadata-Version: 2.1
Name: lprp-core
Version: 1.0.0
Summary: Bei Profit bei Simon melden, bei Problemen bei Lars melden
Author: Simon Berndt
Author-email: berndts.tin21@student.dhbw-heidenheim.de
Requires-Python: >=3.10,<4.0
Classifier: Programming Language :: Python :: 3
Classifier: Programming Language :: Python :: 3.10
Classifier: Programming Language :: Python :: 3.11
Requires-Dist: pydantic (>=1.10.6,<2.0.0)
Requires-Dist: requests (>=2.28.1,<3.0.0)
Requires-Dist: sqlalchemy (>=2.0.4,<3.0.0)
